quilbert/__init__.py
quilbert/__main__.py
quilbert/quilbert.py
quilbert-0.0.1.dist-info/LICENSE
quilbert-0.0.1.dist-info/METADATA
quilbert-0.0.1.dist-info/WHEEL
quilbert-0.0.1.dist-info/entry_points.txt
quilbert-0.0.1.dist-info/top_level.txt
quilbert-0.0.1.dist-info/RECORD
