Metadata-Version: 2.1
Name: quilbert
Version: 0.0.1
Summary: Friendly ai voice assistant
Home-page: https://github.com/rowland-208/quilbert
Author: James Rowland
Author-email: rowland.208@gmail.com
Project-URL: Bug Tracker, https://github.com/rowland-208/quilbert/issues
Classifier: License :: OSI Approved :: MIT License
Classifier: Operating System :: OS Independent
Classifier: Programming Language :: Python
Classifier: Programming Language :: Python :: 3
Classifier: Programming Language :: Python :: 3.10
Requires-Python: >=3.10
License-File: LICENSE
Requires-Dist: openai (==0.27.2)
Requires-Dist: openai-whisper (==20230314)
Requires-Dist: numpy (==1.23.5)
Requires-Dist: pvcobra (==1.2.0)
Requires-Dist: pvporcupine (==2.1.4)
Requires-Dist: PyAudio (==0.2.13)
Requires-Dist: pyttsx3 (==2.90)
Requires-Dist: python-statemachine (==2.0.0)
